glider_ingest/__init__.py
glider_ingest/dataset_attrs.py
glider_ingest/example.py
glider_ingest/gridded_attrs.py
glider_ingest/gridder.py
glider_ingest/processor.py
glider_ingest/utils.py
glider_ingest/variable.py
glider_ingest-1.1.23.dist-info/licenses/LICENSE
glider_ingest-1.1.23.dist-info/METADATA
glider_ingest-1.1.23.dist-info/WHEEL
glider_ingest-1.1.23.dist-info/RECORD
