Metadata-Version: 2.4
Name: glider-ingest
Version: 1.1.23
Summary: Package for GERG to ingest raw glider data into NetCDF files
License-File: LICENSE
Keywords: GERG,TAMU,glider,ingest,netcdf,python,data
Author: Alec
Author-email: alecmkrueger@tamu.edu
Maintainer: Alec
Maintainer-email: alecmkrueger@tamu.edu
Requires-Python: >=3.12,<3.14
Classifier: Programming Language :: Python :: 3
Classifier: Programming Language :: Python :: 3.12
Classifier: Programming Language :: Python :: 3.13
Requires-Dist: attrs (>=23.2.0,<24.0.0)
Requires-Dist: dask (>=2024.8.2,<2025.0.0)
Requires-Dist: dask-expr (>=1.1.13,<2.0.0)
Requires-Dist: dbdreader (>=0.5.7,<0.6.0)
Requires-Dist: gsw (>=3.6.19,<4.0.0)
Requires-Dist: natsort (>=8.4.0,<9.0.0)
Requires-Dist: netcdf4 (>=1.7.1.post1,<2.0.0)
Requires-Dist: numpy (>=2.0.1,<3.0.0)
Requires-Dist: pandas (>=2.2.2,<3.0.0)
Requires-Dist: scipy (>=1.14.0,<2.0.0)
Requires-Dist: xarray (>=2024.6.0,<2025.0.0)
